{
    "result": true,
    "data": {
        "@context": "https://schema.org/",
        "@type": "Product",
        "name": "Система охлаждения ID-Cooling DASHFLOW 360 XT PRO",
        "description": "СЖО ID-Cooling DASHFLOW 360 XT PRO представляет собой высокопроизводительную систему жидкостного охлаждения, предназначенную для охлаждения высокопроизводительных процессоров. Эта система оснащена 360-мм радиатором и тремя 120-мм вентиляторами с частотой вращения от 900 до 2000 об/мин и уровнем шума 32,5 дБ. Вентиляторы имеют высокую скорость воздушного потока, достигающую 85 CFM, что обеспечивает эффективное охлаждение. \nЭта система совместима с широким спектром сокетов, включая Intel LGA 1700, LGA 1200, LGA 115X, LGA2066, LGA 2011 и AMD AM5, AM4. СЖО ID-Cooling DASHFLOW 360 XT PRO имеет максимальную тепловую мощность (TDP) 300 Вт, что позволяет ей эффективно охлаждать даже самые мощные процессоры. Благодаря своей высокой производительности и универсальной совместимости, эта система является отличным выбором для пользователей, требующих высокопроизводительного охлаждения для своих компьютерных систем.",
        "sku": "5486002",
        "offers": {
            "@type": "Offer",
            "url": "https://www.dns-shop.ru/product/f9325d4d6356d582/sistema-okhlazdenia-id-cooling-dashflow-360-xt-pro/",
            "availability": "https://schema.org/InStock",
            "price": 11999,
            "priceCurrency": "RUB"
        },
        "image": [
            "https://c.dns-shop.ru/thumb/st1/fit/300/300/5b48b98d229d6f3c00f0d623194dab6a/e89c8e2aeb1a10c41a0b405515eee8bfc00e63b4df5f15f1424207080be37f84.jpg",
            "https://c.dns-shop.ru/thumb/st1/fit/300/300/f1fbcb528783c2b99bf6c85bde5c0e18/2fccb2652ee32eaebc37f72d4d4939bc683f2158b867eea74b20d729bcfc6663.jpg",
            "https://c.dns-shop.ru/thumb/st1/fit/300/300/0866aa3a53485f69ecae1ed97272f371/ef0172c81e9f9630d50263cb763670c94a08d6805605ea077b3289535019de63.jpg"
        ],
        "brand": {
            "@type": "Brand",
            "name": "ID-Cooling"
        }
    },
    "message": "",
    "errors": []
}